sprag/auto_context.py
sprag/auto_query.py
sprag/chunk_db.py
sprag/create_kb.py
sprag/document_parsing.py
sprag/embedding.py
sprag/knowledge_base.py
sprag/llm.py
sprag/reranker.py
sprag/rse.py
sprag/vector_db.py
sprag-0.0.1.dist-info/LICENSE
sprag-0.0.1.dist-info/METADATA
sprag-0.0.1.dist-info/WHEEL
sprag-0.0.1.dist-info/top_level.txt
sprag-0.0.1.dist-info/RECORD
