Metadata-Version: 2.1
Name: sprag
Version: 0.0.1
Summary: spRAG
Home-page: https://github.com/SuperpoweredAI/spRAG
Author: Superpowered AI
Author-email: zach@superpowered.ai
License: MIT License
Project-URL: Homepage, https://github.com/SuperpoweredAI/spRAG
Project-URL: Documentation, https://github.com/SuperpoweredAI/spRAG
Project-URL: Contact, https://github.com/SuperpoweredAI/spRAG
Classifier: Development Status :: 3 - Alpha
Classifier: Intended Audience :: Developers
Classifier: Intended Audience :: Science/Research
Classifier: License :: OSI Approved :: MIT License
Classifier: Operating System :: OS Independent
Classifier: Programming Language :: Python :: 3.9
Classifier: Programming Language :: Python :: 3.10
Classifier: Programming Language :: Python :: 3.11
Classifier: Programming Language :: Python :: 3.12
Classifier: Topic :: Database
Classifier: Topic :: Software Development
Classifier: Topic :: Software Development :: Libraries
Classifier: Topic :: Software Development :: Libraries :: Application Frameworks
Classifier: Topic :: Software Development :: Libraries :: Python Modules
Requires-Python: >=3.9
License-File: LICENSE
Requires-Dist: openai >=1.21.2
Requires-Dist: anthropic >=0.18.1
Requires-Dist: cohere >=4.37
Requires-Dist: voyageai >=0.2.2
Requires-Dist: tiktoken >=0.3.3
Requires-Dist: faiss-cpu
Requires-Dist: instructor
Requires-Dist: pydantic
Requires-Dist: typing
Requires-Dist: scikit-learn
Requires-Dist: numpy
Requires-Dist: langchain-text-splitters
Requires-Dist: PyPDF2
Requires-Dist: docx2txt
Requires-Dist: pandas
